[
  {
    "location": "STARDUST COFFEE AND VIDEO || ORLANDO, FL || WITH LEG BITERS AND LELE AND THE SPITTERS",
    "time": "5/31/25 @ 7:00pm",
    "price": "$10 AT THE DOOR",
    "ticket": "",
    "selling": false 
  },
  {
    "location": "SAVVY VINYL || MELBOURNE, FL || CONNOR'S GRADUATION PARTY",
    "time": "6/1/25 @ 5:00pm",
    "price": "$11 AT THE DOOR",
    "ticket": "",
    "selling": false
  },
  {
    "location": "TUFFY'S MUSIC BOX || SANFORD, FL || WITH CANNIBAL KIDS AND BUKO BOYS",
    "time": "6/8/25 @ 7:00pm",
    "price": "$15 ADVANCED, $22 DAY OF SHOW",
    "ticket": "https://www.ticketweb.com/event/cannibal-kids-x-buko-boys-tuffys-music-box-tickets/14383093?pl=tuffys&irgwc=1&clickid=Q1J0yQ2S8xyPWJWUS5TJ82YBUksTCbQZ3y-b1I0&camefrom=CFC_BUYAT_219208&impradid=219208&REFERRAL_ID=tmfeedbuyat219208&wt.mc_id=aff_BUYAT_219208&utm_source=219208-Bandsintown&impradname=Bandsintown&utm_medium=affiliate&ircid=4272",
    "selling": true 
  }
]
